<banlist>
    <ban nick="Bucaphelus_Watsons" serial="2608FF441B1A0656F3024EA889BB70E4" banner="Antonio_Johnson" reason="Received 1 admin warnings over multiple accounts." time="1420888403"></ban>
    <ban serial="695BBF36690700D2C4D6DD43904BA902" banner="Samuel_Dunston" reason="Marked as unban time. (168 Hours)" time="1423057101" unban="1423661901"></ban>
    <ban serial="3529252175430C4AE7CE1D3282D3E2E4" banner="Sara_Ward" reason="Unban time (120 Hours)" time="1423221662" unban="1423653662"></ban>
    <ban serial="1727B3BC57FA03A398D48262F7B3A0F2" banner="Sara_Ward" reason="Unban time (120 Hours)" time="1423221697" unban="1423653697"></ban>
    <ban nick="Owl.Player.6738" serial="F80013C5B68BD30B4881736758A40082" banner="Dustin_Bryant" reason="Time-out for rules studying. (72 Hours)" time="1423394900" unban="1423654100"></ban>
    <ban serial="C4AEEC8AA4782B666AB65B2B67274A54" banner="Tyrese_Campbell" reason="Spraying tags on Government property (More than 3 times) (72 Hours)" time="1423396526" unban="1423655726"></ban>
    <ban serial="9C8BA21777967637B74AC80C14D0C1F2" banner="Jimbo_Bodine" reason="Telling a player to commit suicide (72 Hours)" time="1423556455" unban="1423815655"></ban>
    <ban nick="Christian_Hughes" serial="9EF821DBB5AC5567A347EF9B66A76DE4" banner="Clement_Knight" reason="ExcessiveTrolliing|Exessive admin history, needs a break. (48 Hours)" time="1423594224" unban="1423767024"></ban>
</banlist>
